MsSql/MsSql.py
MsSql/__init__.py
tests/__init__.py
tests/test_mssql.py
mssql-1.0.0.dist-info/LICENSE
mssql-1.0.0.dist-info/METADATA
mssql-1.0.0.dist-info/WHEEL
mssql-1.0.0.dist-info/top_level.txt
mssql-1.0.0.dist-info/RECORD
